{
  "name": "tost",
  "rules": {
    "prog": {
      "type": "REPEAT",
      "content": {
        "type": "SYMBOL",
        "name": "item"
      }
    },
    "item": {
      "type": "CHOICE",
      "members": [
        {
          "type": "SYMBOL",
          "name": "func"
        },
        {
          "type": "SYMBOL",
          "name": "externdecl"
        }
      ]
    },
    "id": {
      "type": "PATTERN",
      "value": "[a-zA-Z_]\\w*"
    },
    "comment": {
      "type": "SEQ",
      "members": [
        {
          "type": "FIELD",
          "name": "start",
          "content": {
            "type": "ALIAS",
            "content": {
              "type": "STRING",
              "value": "//"
            },
            "named": false,
            "value": "comment_start"
          }
        },
        {
          "type": "FIELD",
          "name": "content",
          "content": {
            "type": "ALIAS",
            "content": {
              "type": "PATTERN",
              "value": "[^\\r\\n]*"
            },
            "named": false,
            "value": "comment_content"
          }
        }
      ]
    },
    "_fun": {
      "type": "CHOICE",
      "members": [
        {
          "type": "STRING",
          "value": "fun"
        },
        {
          "type": "STRING",
          "value": "toaster"
        }
      ]
    },
    "externdecl": {
      "type": "SEQ",
      "members": [
        {
          "type": "STRING",
          "value": "extern"
        },
        {
          "type": "SYMBOL",
          "name": "_fun"
        },
        {
          "type": "SYMBOL",
          "name": "id"
        },
        {
          "type": "STRING",
          "value": "("
        },
        {
          "type": "CHOICE",
          "members": [
            {
              "type": "SYMBOL",
              "name": "args"
            },
            {
              "type": "BLANK"
            }
          ]
        },
        {
          "type": "STRING",
          "value": ")"
        },
        {
          "type": "CHOICE",
          "members": [
            {
              "type": "SEQ",
              "members": [
                {
                  "type": "STRING",
                  "value": ":"
                },
                {
                  "type": "SYMBOL",
                  "name": "ty"
                }
              ]
            },
            {
              "type": "BLANK"
            }
          ]
        },
        {
          "type": "STRING",
          "value": ";"
        }
      ]
    },
    "func": {
      "type": "SEQ",
      "members": [
        {
          "type": "SYMBOL",
          "name": "_fun"
        },
        {
          "type": "SYMBOL",
          "name": "id"
        },
        {
          "type": "STRING",
          "value": "("
        },
        {
          "type": "CHOICE",
          "members": [
            {
              "type": "SYMBOL",
              "name": "args"
            },
            {
              "type": "BLANK"
            }
          ]
        },
        {
          "type": "STRING",
          "value": ")"
        },
        {
          "type": "CHOICE",
          "members": [
            {
              "type": "SEQ",
              "members": [
                {
                  "type": "STRING",
                  "value": ":"
                },
                {
                  "type": "SYMBOL",
                  "name": "ty"
                }
              ]
            },
            {
              "type": "BLANK"
            }
          ]
        },
        {
          "type": "SYMBOL",
          "name": "block"
        }
      ]
    },
    "arg": {
      "type": "SEQ",
      "members": [
        {
          "type": "SYMBOL",
          "name": "id"
        },
        {
          "type": "STRING",
          "value": ":"
        },
        {
          "type": "SYMBOL",
          "name": "ty"
        }
      ]
    },
    "args": {
      "type": "SEQ",
      "members": [
        {
          "type": "SYMBOL",
          "name": "arg"
        },
        {
          "type": "REPEAT",
          "content": {
            "type": "SEQ",
            "members": [
              {
                "type": "STRING",
                "value": ","
              },
              {
                "type": "SYMBOL",
                "name": "arg"
              }
            ]
          }
        }
      ]
    },
    "ty": {
      "type": "CHOICE",
      "members": [
        {
          "type": "STRING",
          "value": "i64"
        },
        {
          "type": "STRING",
          "value": "i8"
        },
        {
          "type": "STRING",
          "value": "bool"
        },
        {
          "type": "STRING",
          "value": "str"
        },
        {
          "type": "SEQ",
          "members": [
            {
              "type": "STRING",
              "value": "["
            },
            {
              "type": "SYMBOL",
              "name": "ty"
            },
            {
              "type": "STRING",
              "value": "]"
            }
          ]
        },
        {
          "type": "STRING",
          "value": "unit"
        }
      ]
    },
    "block": {
      "type": "SEQ",
      "members": [
        {
          "type": "STRING",
          "value": "{"
        },
        {
          "type": "REPEAT",
          "content": {
            "type": "SYMBOL",
            "name": "stmt"
          }
        },
        {
          "type": "STRING",
          "value": "}"
        }
      ]
    },
    "stmt": {
      "type": "CHOICE",
      "members": [
        {
          "type": "SEQ",
          "members": [
            {
              "type": "STRING",
              "value": "let"
            },
            {
              "type": "SYMBOL",
              "name": "id"
            },
            {
              "type": "STRING",
              "value": "="
            },
            {
              "type": "SYMBOL",
              "name": "expr"
            },
            {
              "type": "STRING",
              "value": ";"
            }
          ]
        },
        {
          "type": "SEQ",
          "members": [
            {
              "type": "SYMBOL",
              "name": "id"
            },
            {
              "type": "STRING",
              "value": "="
            },
            {
              "type": "SYMBOL",
              "name": "expr"
            },
            {
              "type": "STRING",
              "value": ";"
            }
          ]
        },
        {
          "type": "SEQ",
          "members": [
            {
              "type": "SYMBOL",
              "name": "id"
            },
            {
              "type": "STRING",
              "value": "["
            },
            {
              "type": "SYMBOL",
              "name": "expr"
            },
            {
              "type": "STRING",
              "value": "]"
            },
            {
              "type": "STRING",
              "value": "="
            },
            {
              "type": "SYMBOL",
              "name": "expr"
            },
            {
              "type": "STRING",
              "value": ";"
            }
          ]
        },
        {
          "type": "SEQ",
          "members": [
            {
              "type": "SYMBOL",
              "name": "fncall"
            },
            {
              "type": "STRING",
              "value": ";"
            }
          ]
        },
        {
          "type": "SEQ",
          "members": [
            {
              "type": "STRING",
              "value": "return"
            },
            {
              "type": "SYMBOL",
              "name": "expr"
            },
            {
              "type": "STRING",
              "value": ";"
            }
          ]
        },
        {
          "type": "SEQ",
          "members": [
            {
              "type": "STRING",
              "value": "return"
            },
            {
              "type": "STRING",
              "value": ";"
            }
          ]
        },
        {
          "type": "SEQ",
          "members": [
            {
              "type": "STRING",
              "value": "if"
            },
            {
              "type": "SYMBOL",
              "name": "expr"
            },
            {
              "type": "SYMBOL",
              "name": "block"
            }
          ]
        },
        {
          "type": "SEQ",
          "members": [
            {
              "type": "STRING",
              "value": "if"
            },
            {
              "type": "SYMBOL",
              "name": "expr"
            },
            {
              "type": "SYMBOL",
              "name": "block"
            },
            {
              "type": "STRING",
              "value": "else"
            },
            {
              "type": "SYMBOL",
              "name": "block"
            }
          ]
        },
        {
          "type": "SEQ",
          "members": [
            {
              "type": "STRING",
              "value": "loop"
            },
            {
              "type": "SYMBOL",
              "name": "block"
            }
          ]
        },
        {
          "type": "SEQ",
          "members": [
            {
              "type": "STRING",
              "value": "break"
            },
            {
              "type": "STRING",
              "value": ";"
            }
          ]
        }
      ]
    },
    "bop": {
      "type": "CHOICE",
      "members": [
        {
          "type": "PREC_LEFT",
          "value": 100,
          "content": {
            "type": "STRING",
            "value": "*"
          }
        },
        {
          "type": "PREC_LEFT",
          "value": 90,
          "content": {
            "type": "STRING",
            "value": "+"
          }
        },
        {
          "type": "PREC_LEFT",
          "value": 90,
          "content": {
            "type": "STRING",
            "value": "-"
          }
        },
        {
          "type": "PREC_LEFT",
          "value": 80,
          "content": {
            "type": "STRING",
            "value": "<<"
          }
        },
        {
          "type": "PREC_LEFT",
          "value": 80,
          "content": {
            "type": "STRING",
            "value": ">>"
          }
        },
        {
          "type": "PREC_LEFT",
          "value": 80,
          "content": {
            "type": "STRING",
            "value": ">>>"
          }
        },
        {
          "type": "PREC_LEFT",
          "value": 70,
          "content": {
            "type": "STRING",
            "value": "<"
          }
        },
        {
          "type": "PREC_LEFT",
          "value": 70,
          "content": {
            "type": "STRING",
            "value": "<="
          }
        },
        {
          "type": "PREC_LEFT",
          "value": 70,
          "content": {
            "type": "STRING",
            "value": ">"
          }
        },
        {
          "type": "PREC_LEFT",
          "value": 70,
          "content": {
            "type": "STRING",
            "value": ">="
          }
        },
        {
          "type": "PREC_LEFT",
          "value": 60,
          "content": {
            "type": "STRING",
            "value": "=="
          }
        },
        {
          "type": "PREC_LEFT",
          "value": 60,
          "content": {
            "type": "STRING",
            "value": "!="
          }
        },
        {
          "type": "PREC_LEFT",
          "value": 50,
          "content": {
            "type": "STRING",
            "value": "&&"
          }
        },
        {
          "type": "PREC_LEFT",
          "value": 40,
          "content": {
            "type": "STRING",
            "value": "||"
          }
        },
        {
          "type": "PREC_LEFT",
          "value": 30,
          "content": {
            "type": "STRING",
            "value": "&"
          }
        },
        {
          "type": "PREC_LEFT",
          "value": 20,
          "content": {
            "type": "STRING",
            "value": "|"
          }
        }
      ]
    },
    "unescaped": {
      "type": "IMMEDIATE_TOKEN",
      "content": {
        "type": "PREC",
        "value": 1,
        "content": {
          "type": "PATTERN",
          "value": "[^\"\\\\]+"
        }
      }
    },
    "escape_seq": {
      "type": "IMMEDIATE_TOKEN",
      "content": {
        "type": "PREC",
        "value": 1,
        "content": {
          "type": "SEQ",
          "members": [
            {
              "type": "STRING",
              "value": "\\"
            },
            {
              "type": "CHOICE",
              "members": [
                {
                  "type": "PATTERN",
                  "value": "x[a-fA-F0-9]{2}"
                },
                {
                  "type": "PATTERN",
                  "value": "[nr\"'\\\\]"
                }
              ]
            }
          ]
        }
      }
    },
    "string": {
      "type": "SEQ",
      "members": [
        {
          "type": "STRING",
          "value": "\""
        },
        {
          "type": "REPEAT",
          "content": {
            "type": "CHOICE",
            "members": [
              {
                "type": "SYMBOL",
                "name": "unescaped"
              },
              {
                "type": "SYMBOL",
                "name": "escape_seq"
              }
            ]
          }
        },
        {
          "type": "STRING",
          "value": "\""
        }
      ]
    },
    "char": {
      "type": "SEQ",
      "members": [
        {
          "type": "STRING",
          "value": "'"
        },
        {
          "type": "CHOICE",
          "members": [
            {
              "type": "IMMEDIATE_TOKEN",
              "content": {
                "type": "PREC",
                "value": 1,
                "content": {
                  "type": "PATTERN",
                  "value": "[^'\\\\]"
                }
              }
            },
            {
              "type": "SYMBOL",
              "name": "escape_seq"
            }
          ]
        },
        {
          "type": "STRING",
          "value": "'"
        }
      ]
    },
    "integer": {
      "type": "PATTERN",
      "value": "\\d+"
    },
    "_literal": {
      "type": "CHOICE",
      "members": [
        {
          "type": "SYMBOL",
          "name": "integer"
        },
        {
          "type": "SYMBOL",
          "name": "string"
        },
        {
          "type": "SYMBOL",
          "name": "char"
        },
        {
          "type": "STRING",
          "value": "true"
        },
        {
          "type": "STRING",
          "value": "false"
        }
      ]
    },
    "uop": {
      "type": "CHOICE",
      "members": [
        {
          "type": "STRING",
          "value": "-"
        },
        {
          "type": "STRING",
          "value": "!"
        },
        {
          "type": "STRING",
          "value": "~"
        }
      ]
    },
    "expr": {
      "type": "PREC_LEFT",
      "value": 0,
      "content": {
        "type": "CHOICE",
        "members": [
          {
            "type": "SYMBOL",
            "name": "id"
          },
          {
            "type": "SYMBOL",
            "name": "_literal"
          },
          {
            "type": "SEQ",
            "members": [
              {
                "type": "SYMBOL",
                "name": "expr"
              },
              {
                "type": "SYMBOL",
                "name": "bop"
              },
              {
                "type": "SYMBOL",
                "name": "expr"
              }
            ]
          },
          {
            "type": "SEQ",
            "members": [
              {
                "type": "SYMBOL",
                "name": "uop"
              },
              {
                "type": "SYMBOL",
                "name": "expr"
              }
            ]
          },
          {
            "type": "SEQ",
            "members": [
              {
                "type": "STRING",
                "value": "("
              },
              {
                "type": "SYMBOL",
                "name": "expr"
              },
              {
                "type": "STRING",
                "value": ")"
              }
            ]
          },
          {
            "type": "SEQ",
            "members": [
              {
                "type": "SYMBOL",
                "name": "expr"
              },
              {
                "type": "STRING",
                "value": "["
              },
              {
                "type": "SYMBOL",
                "name": "expr"
              },
              {
                "type": "STRING",
                "value": "]"
              }
            ]
          },
          {
            "type": "SYMBOL",
            "name": "fncall"
          },
          {
            "type": "SEQ",
            "members": [
              {
                "type": "STRING",
                "value": "("
              },
              {
                "type": "STRING",
                "value": ")"
              }
            ]
          }
        ]
      }
    },
    "fncall": {
      "type": "SEQ",
      "members": [
        {
          "type": "SYMBOL",
          "name": "id"
        },
        {
          "type": "STRING",
          "value": "("
        },
        {
          "type": "CHOICE",
          "members": [
            {
              "type": "CHOICE",
              "members": [
                {
                  "type": "SEQ",
                  "members": [
                    {
                      "type": "SYMBOL",
                      "name": "expr"
                    },
                    {
                      "type": "REPEAT",
                      "content": {
                        "type": "SEQ",
                        "members": [
                          {
                            "type": "STRING",
                            "value": ","
                          },
                          {
                            "type": "SYMBOL",
                            "name": "expr"
                          }
                        ]
                      }
                    }
                  ]
                },
                {
                  "type": "BLANK"
                }
              ]
            },
            {
              "type": "BLANK"
            }
          ]
        },
        {
          "type": "STRING",
          "value": ")"
        }
      ]
    }
  },
  "extras": [
    {
      "type": "SYMBOL",
      "name": "comment"
    },
    {
      "type": "PATTERN",
      "value": "\\s"
    }
  ],
  "conflicts": [],
  "precedences": [],
  "externals": [],
  "inline": [],
  "supertypes": []
}

